{
    "0": "Potential",
    "1": "Survivor",
    "2": "Attack",
    "3": "Expert",
    "4": "Elemental Attack",
    "5": "Status Attack",
    "6": "Defense",
    "7": "Protection",
    "8": "Health",
    "9": "Rec Speed",
    "10": "Constitution",
    "11": "Stamina",
    "12": "Hunger",
    "13": "Oxygen",
    "14": "Evasion",
    "15": "Evade Distance",
    "16": "Guard",
    "17": "Guard Up",
    "18": "Auto Guard",
    "19": "Transporter",
    "20": "Swimming",
    "21": "Hearing",
    "22": "Poison",
    "23": "Paralysis",
    "24": "Sleep",
    "25": "Stun",
    "26": "Heat Cancel",
    "27": "Cold Cancel",
    "28": "Current Res",
    "29": "Wind-Proof",
    "30": "Tremor-Proof",
    "31": "Mud/Snow",
    "32": "Fire Res",
    "33": "Water Res",
    "34": "Thunder Res",
    "35": "Ice Res",
    "36": "Dragon Res",
    "37": "Blight Res",
    "38": "Speed Setup",
    "39": "Bomb Boost",
    "40": "Combo Rate",
    "41": "Combo Plus",
    "42": "Lasting Power",
    "43": "Wide Range",
    "44": "Eating",
    "45": "Rec Level",
    "46": "Gluttony",
    "47": "BBQ ",
    "48": "Fishing",
    "49": "Dungmaster",
    "50": "Handicraft",
    "51": "Crit Draw",
    "52": "PunishDraw",
    "53": "Fast Charge",
    "54": "Fencing",
    "55": "Sharpness",
    "56": "Sharpening",
    "57": "Free Element",
    "58": "Pierce S Up",
    "59": "Pierce S+",
    "60": "Pellet S Up",
    "61": "Pellet S+",
    "62": "Normal S Up",
    "63": "Normal S+",
    "64": "Crag S+",
    "65": "Clust",
    "66": "Loading",
    "67": "Rapid Fire",
    "68": "Recoil",
    "69": "Reload",
    "70": "Precision",
    "71": "Map",
    "72": "Psychic",
    "73": "Preception",
    "74": "Tranquilzr",
    "75": "Fate",
    "76": "Carving",
    "77": "Gathering",
    "78": "Spd Gather",
    "79": "Whim",
    "80": "Sense",
    "81": "Flame Aura",
    "82": "Theft"
}